py3dframe/__init__.py
py3dframe/__main__.py
py3dframe/__version__.py
py3dframe/frame.py
py3dframe/frame_transform.py
py3dframe/rotation.py
py3dframe/switch_RT_convention.py
py3dframe/manipulations/__init__.py
py3dframe/manipulations/mirror_across_plane.py
py3dframe/manipulations/rotate_around_axis.py
py3dframe/manipulations/translate.py
py3dframe/manipulations/translate_along_axis.py
py3dframe/matrix/O3_project.py
py3dframe/matrix/SO3_project.py
py3dframe/matrix/__init__.py
py3dframe/matrix/is_O3.py
py3dframe/matrix/is_SO3.py
py3dframe/resources/__init__.py
py3dframe/resources/mirroring_across_plane.png
py3dframe/resources/rotation_around_axis.png
py3dframe/resources/train_person_frame.png
py3dframe-1.2.2.dist-info/licenses/LICENSE
py3dframe-1.2.2.dist-info/METADATA
py3dframe-1.2.2.dist-info/WHEEL
py3dframe-1.2.2.dist-info/top_level.txt
py3dframe-1.2.2.dist-info/RECORD
